[
    {
        "name": "嘘呀 ",
        "点攒": "168",
        "差评": "18",
        "内容": "当我真正开始爱自己，我才认识到，所有的痛苦和情感的折磨，都只是在警告我：我的生活违背了自己的本心。——查理·卓别林",
        "图片名": "5def393bd88ae_1.jpg"
    },
    {
        "name": "路上城静 ",
        "点攒": "113",
        "差评": "35",
        "内容": "想听睡前故事",
        "图片名": "5deefc3bbb28d_1.jpg"
    },
    {
        "name": "顾蒙蒙 ",
        "点攒": "130",
        "差评": "30",
        "内容": "偷听到男孩子都讨厌抽烟的女孩子，是吗？",
        "图片名": "5def4feff2089_a_1_1.jpg"
    },
    {
        "name": "Pescado ",
        "点攒": "98",
        "差评": "23",
        "内容": " 婆婆送了本菜谱给媳妇，意图让媳妇学会做菜。结果媳妇很腼腆跟婆婆说：妈您太客气了，您每天那么累，还让我点菜做给我吃，这不太合适呀！"
    },
    {
        "name": "平胸妹子最贴心 ",
        "点攒": "205",
        "差评": "43",
        "内容": "真的可以把鸡蛋放啤酒瓶里",
        "图片名": "5dec1d5118ba6.gif"
    },
    {
        "name": "葩爷 ",
        "点攒": "246",
        "差评": "23",
        "内容": "灵魂木偶师",
        "图片名": "5dc084b12a933.gif"
    },
    {
        "name": "看你紧紧皱眉 ",
        "点攒": "137",
        "差评": "15",
        "内容": "安全感需要自给自足。",
        "图片名": "5dc6e8970830a_1.jpg"
    },
    {
        "name": "死神小一生 ",
        "点攒": "156",
        "差评": "23",
        "内容": "哇哈哈哈哈",
        "图片名": "5de9382776d29.gif"
    },
    {
        "name": "就这样过了 ",
        "点攒": "91",
        "差评": "27",
        "内容": " 你童年最喜欢吃的一款小零食是什么？只能说一款"
    },
    {
        "name": "筱熙她爹 ",
        "点攒": "109",
        "差评": "19",
        "内容": " 刚刚看到一对情侣在路灯下吵架，男孩为了挽回芳心，居然跪了十分钟。没骨气，真TM怂，我当年可刚烈了，足足跪了一个通宵！"
    },
    {
        "name": "关注我的都是大佬 ",
        "点攒": "111",
        "差评": "25",
        "内容": " 每个周末催孩子做作业都是一场恶战。儿子今天趴在地上对爸爸说道：“读书最没有用了，我读六年书，一分钱也没挣着。我这六年要是用来当乞丐，都不知道赚了多少了。”爸爸气愤地冲他喊：“你去要啊去要啊!”儿子低声说：“这个你要想好了，我面前那张纸会不太吉利，至少会写四个字：父母双亡……”."
    },
    {
        "name": "白朗宁·D·霍德孟特 ",
        "点攒": "220",
        "差评": "42",
        "内容": "只好如此了😼",
        "图片名": "5ddce0181827a_1.jpg"
    },
    {
        "name": "笑品百味人生 ",
        "点攒": "417",
        "差评": "43",
        "内容": "他还是那么的优秀",
        "图片名": "5ddf82f1a9566_1.jpg"
    },
    {
        "name": "血色@浪漫E34 ",
        "点攒": "173",
        "差评": "67",
        "内容": "老师笑趴在办公桌上！",
        "图片名": "5ddf7027b5804_1.jpg"
    },
    {
        "name": "我什么都不知道 ",
        "点攒": "125",
        "差评": "25",
        "内容": "东北的朋友告诉一下我，这是真的么",
        "图片名": "5dd781f284ae4_1.jpg"
    },
    {
        "name": "死神小一生 ",
        "点攒": "135",
        "差评": "34",
        "内容": "感觉有点可爱",
        "图片名": "5ddd580e57542_1.jpg"
    },
    {
        "name": "进哥哥 ",
        "点攒": "91",
        "差评": "26",
        "内容": " 地球的年龄是怎么计算出来的？"
    },
    {
        "name": "誉帏 ",
        "点攒": "137",
        "差评": "22",
        "内容": " 结婚时，媳妇带来一个小瓶子，说以后的日子，每惹她哭一次，就往瓶子里滴一滴水，等哪天，瓶子满了，心也一定死了，会毫不犹豫地离开我。前几天我偷偷给那瓶子灌进两大勺水，被媳妇发现了……"
    },
    {
        "name": "关注我的都是大佬 ",
        "点攒": "113",
        "差评": "22",
        "内容": " 一天同学聚会，都说自己工资有多高多高，问道我时我弱弱说：少的可怜，就3000块。大家都笑话我说：确实少的可怜。最后我补了句：老婆发的。全场瞬间沉默，然后惊呼：这才叫土豪啊。。。"
    },
    {
        "name": "关注我的都是大佬 ",
        "点攒": "112",
        "差评": "26",
        "内容": " 我们这期学驾驶的都是年轻人，为了方便与教练管理和联系，建了一个群！今天是个大喜的日子，全体学员都通过了科目二，为了庆祝，群主做的第一件事就是将教练踢出群！"
    },
    {
        "name": "Pescado ",
        "点攒": "131",
        "差评": "22",
        "内容": " 分手那晚，她喝多了，男友抱着送她上车，最后说了句“珍重”。"
    },
    {
        "name": "用户FqzHnf ",
        "点攒": "169",
        "差评": "19",
        "内容": " 大海真的太恐怖了，当年泰坦尼克号出海的时候，我喉咙都喊哑了，不让他们出海。非但不听，居然还把我从电影院赶了出来。"
    },
    {
        "name": "风雨楼台 ",
        "点攒": "134",
        "差评": "15",
        "内容": "猫：你管管你的狗子吧！....",
        "图片名": "5dd7d58ac80b5.gif"
    },
    {
        "name": "繁华已尽 ",
        "点攒": "151",
        "差评": "24",
        "内容": "陪女朋友拍照的你...",
        "图片名": "5dd734022c3da.gif"
    },
    {
        "name": "安之若素 ",
        "点攒": "179",
        "差评": "14",
        "内容": "回头一看，傻了，一脸懵逼~",
        "图片名": "5dbc1a237dbd3.gif"
    },
    {
        "name": "盯裆猫 ",
        "点攒": "146",
        "差评": "24",
        "内容": "晚上看完鬼.片洗漱的你",
        "图片名": "5da0452bc22e9.gif"
    },
    {
        "name": "陌月 ",
        "点攒": "184",
        "差评": "30",
        "内容": "哇。。硬核玩家！",
        "图片名": "5dd71aefee2cd.gif"
    },
    {
        "name": "菲菲 ",
        "点攒": "208",
        "差评": "18",
        "内容": "一位潜水客在海中下潜时，偶遇两周前曾经一起玩过的海豹，双方竟然都认出彼此，海豹还主动求抱抱，抱住就不松手，一定是特别的缘分",
        "图片名": "5da0347b95ef9.gif"
    },
    {
        "name": "Pescado ",
        "点攒": "116",
        "差评": "20",
        "内容": " 不明白了电视里，古代那些大侠一出去，就是两斤酱牛肉一壶好酒，每天最少三顿..."
    },
    {
        "name": "回忆可忆、不可回 ",
        "点攒": "93",
        "差评": "16",
        "内容": " 老两口抱着孙子在街上逛，迎面碰上一中年妇女：真可爱，多大了？老太太抢先回答：再过两个月就六十五啦。"
    },
    {
        "name": "死神小一生 ",
        "点攒": "220",
        "差评": "31",
        "内容": "挺会玩啊！",
        "图片名": "5dd8148ff08d6.gif"
    },
    {
        "name": "死神小一生 ",
        "点攒": "159",
        "差评": "32",
        "内容": "鸟：这次玩大了，谁来救救我",
        "图片名": "5dd816b231364.gif"
    },
    {
        "name": "谢龙辉 ",
        "点攒": "155",
        "差评": "29",
        "内容": "一定会有人助你渡过难关",
        "图片名": "5da02c45ad502.gif"
    },
    {
        "name": "风情你w总 ",
        "点攒": "115",
        "差评": "25",
        "内容": "晚上应酬回家，却发现儿子不见了，找到孩子那一刻父亲笑了",
        "图片名": "5da0a084003be_1.jpg"
    },
    {
        "name": "绿健 ",
        "点攒": "112",
        "差评": "32",
        "内容": "养狗千日，用狗一时",
        "图片名": "5dacaf48332f4.gif"
    },
    {
        "name": "一天到晚爱玩的猫 ",
        "点攒": "160",
        "差评": "18",
        "内容": "养喵百日，用喵一时",
        "图片名": "5dd27bb231f19.gif"
    },
    {
        "name": "崔亚腾 ",
        "点攒": "142",
        "差评": "29",
        "内容": "刚起床的你",
        "图片名": "5dd4df7cbe705.gif"
    },
    {
        "name": "舞月 ",
        "点攒": "122",
        "差评": "24",
        "内容": " 说实话，最怕灯厂的车，刹车灯晃眼，远光灯刺眼。有次一辆A8跟我后头，那远光灯照得我开不了车，我停车把他截停，一问，人家开的近光，俩人研究了半天，那大哥突然激动的说，“兄dei，我知道了，是你的布加迪底盘太低了。”"
    },
    {
        "name": "苦恼的人 ",
        "点攒": "122",
        "差评": "21",
        "内容": "嗯，对，你很凶，吓死我啦，哇。",
        "图片名": "5dd7733b72f75.gif"
    },
    {
        "name": "死灰色 ",
        "点攒": "139",
        "差评": "14",
        "内容": "鹦鹉：咋滴？我还不能玩个大鹏展翅啊？",
        "图片名": "5db99986dd601.gif"
    },
    {
        "name": "生姜 ",
        "点攒": "125",
        "差评": "52",
        "内容": "莫名感觉挺幸福的~~你以后也要像他这样宠我哦",
        "图片名": "5da0fecc1fdb4.gif"
    },
    {
        "name": "獨自等待 ",
        "点攒": "131",
        "差评": "23",
        "内容": "年纪大的人是如何漏脚踝的……哈哈哈哈哈哈哈",
        "图片名": "5dcb654ae3f1c.gif"
    },
    {
        "name": "大忽悠山崎 ",
        "点攒": "157",
        "差评": "20",
        "内容": "婚礼途中发现老公成佛了怎么办？",
        "图片名": "5dd7dc71b7148.gif"
    },
    {
        "name": "花儿开了 ",
        "点攒": "141",
        "差评": "24",
        "内容": " 早晨去楼下买油条，大妈说要2.5元一根。"
    },
    {
        "name": "胖哥聊足球 ",
        "点攒": "114",
        "差评": "24",
        "内容": "教你叠纸飞机中的战斗机",
        "图片名": "5dd3c661cbc77.gif"
    },
    {
        "name": "仐亗 ",
        "点攒": "206",
        "差评": "21",
        "内容": "你没见过的醉拳",
        "图片名": "5dd7c94538125.gif"
    },
    {
        "name": "闹闹 ",
        "点攒": "176",
        "差评": "33",
        "内容": "姑娘，这是想讹个男朋友啊",
        "图片名": "5dd725cb6279a.gif"
    },
    {
        "name": "笑品百味人生 ",
        "点攒": "127",
        "差评": "31",
        "内容": "当代年轻人是如何关灯的…",
        "图片名": "5dd4b1bf507a9.gif"
    },
    {
        "name": "为爱_鼓掌 ",
        "点攒": "166",
        "差评": "22",
        "内容": "好可怜的狗子，看起来好疼啊！😂",
        "图片名": "5dd625d3b0fae.gif"
    },
    {
        "name": "小笼包酱紫 ",
        "点攒": "117",
        "差评": "14",
        "内容": "主人睡觉猫咪用尾巴给主人当眼罩",
        "图片名": "5dd2575b1cb03_1.jpg"
    },
    {
        "name": "城市中人 ",
        "点攒": "232",
        "差评": "29",
        "内容": "妈妈过年终于回家了，母子相拥的这一刻，无数人被感动了！",
        "图片名": "5dd4a064e8b71.gif"
    },
    {
        "name": "人设丿 ",
        "点攒": "163",
        "差评": "24",
        "内容": "这就是天气预报说的局部地区？",
        "图片名": "5dd6718cf30ee.gif"
    },
    {
        "name": "七宝 ",
        "点攒": "130",
        "差评": "44",
        "内容": "女友给男友钱哄男友吃药，他却吃感冒冲剂",
        "图片名": "5d9e87d55aa3c_1.jpg"
    },
    {
        "name": "罗敷 ",
        "点攒": "149",
        "差评": "18",
        "内容": "听到自己的声音是这种感觉",
        "图片名": "5dd4495a441fc_1.jpg"
    },
    {
        "name": "靓靓 ",
        "点攒": "156",
        "差评": "16",
        "内容": "给话痨副驾驶配个方向盘是个好办法",
        "图片名": "5dd515a5a8739.gif"
    },
    {
        "name": "阿呆先生 ",
        "点攒": "129",
        "差评": "11",
        "内容": "和大狗睡在一起，完全没有什么办法",
        "图片名": "5da133959cd23.gif"
    },
    {
        "name": "笑品百味人生 ",
        "点攒": "127",
        "差评": "26",
        "内容": "猫的瞳孔聚焦会变化",
        "图片名": "5dd377c0731d9.gif"
    },
    {
        "name": "世墨子 ",
        "点攒": "150",
        "差评": "16",
        "内容": "猫见到洞就想钻,任何洞",
        "图片名": "5dd3da9d0013a.gif"
    },
    {
        "name": "余生有你 ",
        "点攒": "170",
        "差评": "14",
        "内容": "聪明的金毛自己挣脱狗链",
        "图片名": "5dd287153e9ad.gif"
    },
    {
        "name": "小花花花 ",
        "点攒": "145",
        "差评": "30",
        "内容": "说话的秀恩爱，结果......",
        "图片名": "5dd4a30d4fcf0.gif"
    },
    {
        "name": "江津愚小面 ",
        "点攒": "110",
        "差评": "19",
        "内容": "太宠溺了……别人家的男朋友",
        "图片名": "5dd47c27d773c.gif"
    },
    {
        "name": "山那边的枫林 ",
        "点攒": "121",
        "差评": "17",
        "内容": "去睡沙发吧！这里没有你的位置了！！！",
        "图片名": "5dae3f846294a_1.jpg"
    },
    {
        "name": "烛影不会乱 ",
        "点攒": "344",
        "差评": "37",
        "内容": "你可能是世界上最孤独的steam用户了",
        "图片名": "5dc04285d9071_1.jpg"
    },
    {
        "name": "笑品百味人生 ",
        "点攒": "160",
        "差评": "25",
        "内容": "说话也太不算数了吧！！！",
        "图片名": "5dd4b78d11796_1.jpg"
    },
    {
        "name": "怀疑人生 ",
        "点攒": "158",
        "差评": "16",
        "内容": "我擦，什么情况？？",
        "图片名": "5dd509c1ad707.gif"
    },
    {
        "name": "金月 ",
        "点攒": "142",
        "差评": "11",
        "内容": "粘人精！！！",
        "图片名": "5dd3ac1829c77.gif"
    },
    {
        "name": "游先生 ",
        "点攒": "192",
        "差评": "44",
        "内容": "得此妻，夫复何求",
        "图片名": "5dd1917ec5920_1.jpg"
    },
    {
        "name": "加强 ",
        "点攒": "100",
        "差评": "10",
        "内容": "吃货就是有吃的必醒",
        "图片名": "5dd1758ae0ba9.gif"
    },
    {
        "name": "南南 ",
        "点攒": "309",
        "差评": "69",
        "内容": "我想问一下女生，下图哪个是迪迦奥特曼？",
        "图片名": "5dd28bc2673c3_1.jpg"
    },
    {
        "name": "心之痕 ",
        "点攒": "254",
        "差评": "36",
        "内容": "自行车进化史",
        "图片名": "5dd21c172f697.gif"
    },
    {
        "name": "怀疑人生 ",
        "点攒": "130",
        "差评": "22",
        "内容": "我妈已经三天没有打我了，三天没有打我了",
        "图片名": "5dd1989ad01ad.gif"
    },
    {
        "name": "能认真点吗 ",
        "点攒": "172",
        "差评": "13",
        "内容": "狗子：？？？",
        "图片名": "5dd2b244695f0.gif"
    },
    {
        "name": "雨婷思梦 ",
        "点攒": "164",
        "差评": "20",
        "内容": "妈妈再也不用担心我长智齿了",
        "图片名": "5dd1afe5c4f67.gif"
    },
    {
        "name": "原装正版无添加 ",
        "点攒": "258",
        "差评": "72",
        "内容": "转发这只飞跃的猫，未来一年内什么困难都可以轻松越过！",
        "图片名": "5dcfaddd47fbe_1.jpg"
    },
    {
        "name": "随便了 ",
        "点攒": "172",
        "差评": "19",
        "内容": "哈哈哈哈哈哈哈哈哈哈哈哈哈哈哈哈哈哈",
        "图片名": "5dba6e7d1d94f_1.jpg"
    },
    {
        "name": "滒特 誃瑙菏 ",
        "点攒": "121",
        "差评": "28",
        "内容": "高铁上有的人到底能有多没素质？",
        "图片名": "5dae8c2eaa7ef_1.jpg"
    },
    {
        "name": "糖水菠萝 ",
        "点攒": "126",
        "差评": "18",
        "内容": "猫咪做完绝育后，麻药还没全退...但是一到开饭点...",
        "图片名": "5dbbccf69f99e.gif"
    },
    {
        "name": "诠忄 ",
        "点攒": "142",
        "差评": "21",
        "内容": "这是我见过最喜感的捕鼠器了。你感受过绝望吗？",
        "图片名": "5da9e048b06a8.gif"
    },
    {
        "name": "知鱼之乐 ",
        "点攒": "166",
        "差评": "31",
        "内容": "我滴妈呀，这谁顶得住。",
        "图片名": "5db144d3789fc.gif"
    },
    {
        "name": "墨染锦年 ",
        "点攒": "196",
        "差评": "25",
        "内容": "做单亲爸爸是什么体验？",
        "图片名": "5db1544da5bd1_1.jpg"
    },
    {
        "name": "Pescado ",
        "点攒": "146",
        "差评": "43",
        "内容": " 老王：你怎么秃顶了？"
    },
    {
        "name": "出走的小哪吒 ",
        "点攒": "196",
        "差评": "88",
        "内容": "火狐突击！",
        "图片名": "5d6be8e4396c4.gif"
    },
    {
        "name": "小利酱 ",
        "点攒": "204",
        "差评": "78",
        "内容": "吃到美食的你",
        "图片名": "5d6fbf51adcae.gif"
    },
    {
        "name": "快乐肥皂 ",
        "点攒": "350",
        "差评": "78",
        "内容": "小鸟：爸爸，爸爸，我饿了老爸：听不见，听不见，听不见",
        "图片名": "5d6fd8b09d07a.gif"
    },
    {
        "name": "笑品百味人生 ",
        "点攒": "198",
        "差评": "76",
        "内容": "听奶奶的话，没错的",
        "图片名": "5d6f7017d214e_1.jpg"
    },
    {
        "name": "暖玉烟 ",
        "点攒": "363",
        "差评": "84",
        "内容": "哈哈哈哈哈哈哈哈哈画面感真的强",
        "图片名": "5d6f8fe51c3e4_1.jpg"
    },
    {
        "name": "无极限 ",
        "点攒": "233",
        "差评": "98",
        "内容": "你在你男（女）朋友的手机里发现过什么秘密？",
        "图片名": "5d6f9b1043825_1.jpg"
    },
    {
        "name": "樊笼 ",
        "点攒": "239",
        "差评": "140",
        "内容": "这谁受得住啊？",
        "图片名": "5d6fabfbdbc01.gif"
    },
    {
        "name": "IRISHAHA999 ",
        "点攒": "298",
        "差评": "64",
        "内容": "这是想骗我没进过城吗？？",
        "图片名": "5d6f66341bb8c_1.jpg"
    },
    {
        "name": "言无欲 ",
        "点攒": "419",
        "差评": "65",
        "内容": "老虎：刚刚是不是想还手来着？",
        "图片名": "5d6fd4f5d0216.gif"
    },
    {
        "name": "柳柳 ",
        "点攒": "230",
        "差评": "81",
        "内容": "现在90后员工容易离职，有没有什么办法可以留住他们呢？",
        "图片名": "5d6f91a747384_1.jpg"
    },
    {
        "name": "Pescado ",
        "点攒": "203",
        "差评": "66",
        "内容": "育儿概要，拿走不谢",
        "图片名": "5d6fd0ea91b11_1.jpg"
    },
    {
        "name": "不得姐用户 ",
        "点攒": "349",
        "差评": "96",
        "内容": "有点儿意思",
        "图片名": "5d6f1cd954e0c_1.jpg"
    },
    {
        "name": "梁某人 ",
        "点攒": "338",
        "差评": "38",
        "内容": "正是这么个道理",
        "图片名": "5d708748874b6_1.jpg"
    },
    {
        "name": "农龙泷 ",
        "点攒": "232",
        "差评": "23",
        "内容": "辛苦了饲养员，帮你捶捶背",
        "图片名": "5d64d104b274c.gif"
    },
    {
        "name": "飞起的鱼 ",
        "点攒": "251",
        "差评": "71",
        "内容": " 所谓表白，无非就是你兜里揣着一个苹果，去问对方喜不喜欢苹果，而对方有喜欢橘子鸭梨猕猴桃菠萝草莓等等N种可能，这种情况看运气。而有的人不一样！他们兜里揣的是金条。。"
    },
    {
        "name": "牧马城市 ",
        "点攒": "279",
        "差评": "53",
        "内容": "断了线的木偶",
        "图片名": "5d6f21f6d5962.gif"
    },
    {
        "name": "克莱 ",
        "点攒": "181",
        "差评": "65",
        "内容": "这么小的包包能装什么？",
        "图片名": "5d6bf49e5b401_1.jpg"
    },
    {
        "name": "猪肉吃多了 ",
        "点攒": "309",
        "差评": "64",
        "内容": " 你问我游戏重要还是女朋友重要？"
    },
    {
        "name": "梁尔华 ",
        "点攒": "158",
        "差评": "49",
        "内容": "哈哈哈我每天的健身方式又被发现了",
        "图片名": "5d6e65db0a0d7_1.jpg"
    }
]